pytest_simplehttpserver/__init__.py
pytest_simplehttpserver/pytest_plugin.py
pytest_simplehttpserver/simplehttpserver.py
pytest_simplehttpserver-0.1.2.dist-info/LICENSE
pytest_simplehttpserver-0.1.2.dist-info/METADATA
pytest_simplehttpserver-0.1.2.dist-info/WHEEL
pytest_simplehttpserver-0.1.2.dist-info/entry_points.txt
pytest_simplehttpserver-0.1.2.dist-info/top_level.txt
pytest_simplehttpserver-0.1.2.dist-info/RECORD
