Metadata-Version: 2.1
Name: pytest-simplehttpserver
Version: 0.1.2
Summary: Simple pytest fixture to spin up an HTTP server
Home-page: https://github.com/ppmdo/pytest-simplehttpserver
Author: Pablo Prieto Montes de Oca
Author-email: pabloprieto@live.com
Maintainer: Pablo Prieto Montes de Oca
Maintainer-email: pabloprieto@live.com
License: MIT
Platform: UNKNOWN
Classifier: Development Status :: 4 - Beta
Classifier: Framework :: Pytest
Classifier: Intended Audience :: Developers
Classifier: Topic :: Software Development :: Testing
Classifier: Programming Language :: Python
Classifier: Programming Language :: Python :: 3
Classifier: Programming Language :: Python :: 3.5
Classifier: Programming Language :: Python :: 3.6
Classifier: Programming Language :: Python :: 3.7
Classifier: Programming Language :: Python :: 3.8
Classifier: Programming Language :: Python :: 3 :: Only
Classifier: Programming Language :: Python :: Implementation :: CPython
Classifier: Programming Language :: Python :: Implementation :: PyPy
Classifier: Operating System :: OS Independent
Classifier: License :: OSI Approved :: MIT License
Requires-Python: >=3.5
License-File: LICENSE
